[{    
    "id": "0",
    "icon": "../../../public/icons/html.svg",
    "name": "HTML",
    "level": "99"
},
{    
    "id": "1",
    "icon": "../../../public/icons/css.svg",
    "name": "CSS",
    "level": "99"
},
{    
    "id": "2",
    "icon": "../../../public/icons/js.svg",
    "name": "Javascript",
    "level": "80"
},
{    
    "id": "3",
    "icon": "../../../public/icons/php.svg",
    "name": "PHP",
    "level": "60"
},
{    
    "id": "4",
    "icon": "../../../public/icons/react.svg",
    "name": "React",
    "level": "60"
},
{    
    "id": "5",
    "icon": "../../../public/icons/sass.svg",
    "name": "SASS",
    "level": "90"
},
{    
    "id": "6",
    "icon": "../../../public/icons/bootstrap.svg",
    "name": "Bootstrap",
    "level": "50"
},
{    
    "id": "7",
    "icon": "../../../public/icons/tailwind.svg",
    "name": "Tailwind",
    "level": "50"
},
{    
    "id": "8",
    "icon": "../../../public/icons/mysql.svg",
    "name": "MySQL",
    "level": "40"
},
{    
    "id": "9",
    "icon": "../../../public/icons/mongodb.svg",
    "name": "MongoDB",
    "level": "60"
}]